{
  "meta": {
    "chronografVersion": "1.6.2",
    "sources": {
      "0": {
        "name": "My Influx",
        "link": "/chronograf/v1/sources/0"
      },
      "1": {
        "name": "My InfluxDB",
        "link": "/chronograf/v1/sources/1"
      },
      "2": {
        "name": "SecurEdge Networks",
        "link": "/chronograf/v1/sources/2"
      }
    }
  },
  "dashboard": {
    "id": 4,
    "cells": [
      {
        "i": "7c734c30-7e7b-41a9-a410-7dbcd4eb7824",
        "x": 0,
        "y": 13,
        "w": 12,
        "h": 4,
        "name": "CQs Executed/Min",
        "queries": [
          {
            "query": "SELECT non_negative_derivative(mean(/.*/),60s) FROM \"_internal\"..\"cq\" WHERE time > :dashboardTime: GROUP BY hostname, time(:interval:) fill(null)",
            "queryConfig": {
              "database": "",
              "measurement": "",
              "retentionPolicy": "",
              "fields": [],
              "tags": {},
              "groupBy": {
                "time": "",
                "tags": []
              },
              "areTagsAccepted": false,
              "rawText": "SELECT non_negative_derivative(mean(/.*/),60s) FROM \"_internal\"..\"cq\" WHERE time > :dashboardTime: GROUP BY hostname, time(:interval:) fill(null)",
              "range": null,
              "shifts": null
            },
            "source": ""
          }
        ],
        "axes": {
          "x": {
            "bounds": [
              "",
              ""
            ],
            "label": "",
            "prefix": "",
            "suffix": "",
            "base": "10",
            "scale": "linear"
          },
          "y": {
            "bounds": [
              "",
              ""
            ],
            "label": "",
            "prefix": "",
            "suffix": "",
            "base": "10",
            "scale": "linear"
          },
          "y2": {
            "bounds": [
              "",
              ""
            ],
            "label": "",
            "prefix": "",
            "suffix": "",
            "base": "10",
            "scale": "linear"
          }
        },
        "type": "line",
        "colors": [
          {
            "id": "731cb197-e6ac-48d5-974f-03c32ba864de",
            "type": "scale",
            "hex": "#31C0F6",
            "name": "Nineteen Eighty Four",
            "value": "0"
          },
          {
            "id": "a64b1fce-50e3-471c-a78b-2df4ed07798d",
            "type": "scale",
            "hex": "#A500A5",
            "name": "Nineteen Eighty Four",
            "value": "0"
          },
          {
            "id": "9211508a-a22c-4000-a71b-96b17c14b447",
            "type": "scale",
            "hex": "#FF7E27",
            "name": "Nineteen Eighty Four",
            "value": "0"
          }
        ],
        "legend": {},
        "tableOptions": {
          "verticalTimeAxis": false,
          "sortBy": {
            "internalName": "",
            "displayName": "",
            "visible": false
          },
          "wrapping": "",
          "fixFirstColumn": false
        },
        "fieldOptions": [],
        "timeFormat": "",
        "decimalPlaces": {
          "isEnforced": false,
          "digits": 3
        },
        "links": {
          "self": "/chronograf/v1/dashboards/4/cells/7c734c30-7e7b-41a9-a410-7dbcd4eb7824"
        }
      },
      {
        "i": "91ae151d-5c0e-49f8-97f0-24e29a8a13ee",
        "x": 0,
        "y": 9,
        "w": 6,
        "h": 4,
        "name": "Heap Size",
        "queries": [
          {
            "query": "SELECT mean(\"HeapInUse\") FROM \"_internal\"..\"runtime\" WHERE time > :dashboardTime: GROUP BY time(:interval:), \"hostname\" fill(null)",
            "queryConfig": {
              "database": "_internal",
              "measurement": "runtime",
              "retentionPolicy": "",
              "fields": [
                {
                  "value": "mean",
                  "type": "func",
                  "alias": "",
                  "args": [
                    {
                      "value": "HeapInUse",
                      "type": "field",
                      "alias": ""
                    }
                  ]
                }
              ],
              "tags": {},
              "groupBy": {
                "time": "auto",
                "tags": [
                  "hostname"
                ]
              },
              "areTagsAccepted": false,
              "fill": "null",
              "rawText": null,
              "range": null,
              "shifts": null
            },
            "source": ""
          }
        ],
        "axes": {
          "x": {
            "bounds": [
              "",
              ""
            ],
            "label": "",
            "prefix": "",
            "suffix": "",
            "base": "10",
            "scale": "linear"
          },
          "y": {
            "bounds": [
              "",
              ""
            ],
            "label": "",
            "prefix": "",
            "suffix": "",
            "base": "2",
            "scale": "linear"
          },
          "y2": {
            "bounds": [
              "",
              ""
            ],
            "label": "",
            "prefix": "",
            "suffix": "",
            "base": "10",
            "scale": "linear"
          }
        },
        "type": "line",
        "colors": [
          {
            "id": "731cb197-e6ac-48d5-974f-03c32ba864de",
            "type": "scale",
            "hex": "#31C0F6",
            "name": "Nineteen Eighty Four",
            "value": "0"
          },
          {
            "id": "a64b1fce-50e3-471c-a78b-2df4ed07798d",
            "type": "scale",
            "hex": "#A500A5",
            "name": "Nineteen Eighty Four",
            "value": "0"
          },
          {
            "id": "9211508a-a22c-4000-a71b-96b17c14b447",
            "type": "scale",
            "hex": "#FF7E27",
            "name": "Nineteen Eighty Four",
            "value": "0"
          }
        ],
        "legend": {},
        "tableOptions": {
          "verticalTimeAxis": false,
          "sortBy": {
            "internalName": "",
            "displayName": "",
            "visible": false
          },
          "wrapping": "",
          "fixFirstColumn": false
        },
        "fieldOptions": [],
        "timeFormat": "",
        "decimalPlaces": {
          "isEnforced": false,
          "digits": 3
        },
        "links": {
          "self": "/chronograf/v1/dashboards/4/cells/91ae151d-5c0e-49f8-97f0-24e29a8a13ee"
        }
      },
      {
        "i": "d5ce7adb-aba7-4f46-aa32-3081f90e5b5e",
        "x": 6,
        "y": 9,
        "w": 6,
        "h": 4,
        "name": "Shard Write Errors",
        "queries": [
          {
            "query": "SELECT non_negative_derivative(max(\"writeError\"), 10s) FROM \"_internal\"..\"write\" WHERE time > :dashboardTime: GROUP BY time(:interval:), \"hostname\" fill(null)",
            "queryConfig": {
              "database": "",
              "measurement": "",
              "retentionPolicy": "",
              "fields": [],
              "tags": {},
              "groupBy": {
                "time": "",
                "tags": []
              },
              "areTagsAccepted": false,
              "rawText": "SELECT non_negative_derivative(max(\"writeError\"), 10s) FROM \"_internal\"..\"write\" WHERE time > :dashboardTime: GROUP BY time(:interval:), \"hostname\" fill(null)",
              "range": null,
              "shifts": null
            },
            "source": ""
          }
        ],
        "axes": {
          "x": {
            "bounds": [
              "",
              ""
            ],
            "label": "",
            "prefix": "",
            "suffix": "",
            "base": "10",
            "scale": "linear"
          },
          "y": {
            "bounds": [
              "",
              ""
            ],
            "label": "",
            "prefix": "",
            "suffix": "",
            "base": "10",
            "scale": "linear"
          },
          "y2": {
            "bounds": [
              "",
              ""
            ],
            "label": "",
            "prefix": "",
            "suffix": "",
            "base": "10",
            "scale": "linear"
          }
        },
        "type": "line",
        "colors": [
          {
            "id": "731cb197-e6ac-48d5-974f-03c32ba864de",
            "type": "scale",
            "hex": "#31C0F6",
            "name": "Nineteen Eighty Four",
            "value": "0"
          },
          {
            "id": "a64b1fce-50e3-471c-a78b-2df4ed07798d",
            "type": "scale",
            "hex": "#A500A5",
            "name": "Nineteen Eighty Four",
            "value": "0"
          },
          {
            "id": "9211508a-a22c-4000-a71b-96b17c14b447",
            "type": "scale",
            "hex": "#FF7E27",
            "name": "Nineteen Eighty Four",
            "value": "0"
          }
        ],
        "legend": {},
        "tableOptions": {
          "verticalTimeAxis": false,
          "sortBy": {
            "internalName": "",
            "displayName": "",
            "visible": false
          },
          "wrapping": "",
          "fixFirstColumn": false
        },
        "fieldOptions": [],
        "timeFormat": "",
        "decimalPlaces": {
          "isEnforced": false,
          "digits": 3
        },
        "links": {
          "self": "/chronograf/v1/dashboards/4/cells/d5ce7adb-aba7-4f46-aa32-3081f90e5b5e"
        }
      },
      {
        "i": "7e15b93e-e7ad-49b6-bffc-19d48867a21d",
        "x": 0,
        "y": 5,
        "w": 6,
        "h": 4,
        "name": "Series Cardinality by Database & Number of Measurements by Database",
        "queries": [
          {
            "query": "SELECT max(\"numSeries\") AS \"Series Cardinality\" FROM \"_internal\"..\"database\" WHERE time > :dashboardTime:  GROUP BY time(:interval:), \"database\" fill(null)",
            "queryConfig": {
              "database": "_internal",
              "measurement": "database",
              "retentionPolicy": "",
              "fields": [
                {
                  "value": "max",
                  "type": "func",
                  "alias": "Series Cardinality",
                  "args": [
                    {
                      "value": "numSeries",
                      "type": "field",
                      "alias": ""
                    }
                  ]
                }
              ],
              "tags": {},
              "groupBy": {
                "time": "auto",
                "tags": [
                  "database"
                ]
              },
              "areTagsAccepted": false,
              "fill": "null",
              "rawText": null,
              "range": null,
              "shifts": null
            },
            "source": ""
          },
          {
            "query": "SELECT max(\"numMeasurements\") AS \"Measurements\" FROM \"_internal\"..\"database\" WHERE time > :dashboardTime:  GROUP BY time(:interval:), \"database\" fill(null)",
            "queryConfig": {
              "database": "_internal",
              "measurement": "database",
              "retentionPolicy": "",
              "fields": [
                {
                  "value": "max",
                  "type": "func",
                  "alias": "Measurements",
                  "args": [
                    {
                      "value": "numMeasurements",
                      "type": "field",
                      "alias": ""
                    }
                  ]
                }
              ],
              "tags": {},
              "groupBy": {
                "time": "auto",
                "tags": [
                  "database"
                ]
              },
              "areTagsAccepted": false,
              "fill": "null",
              "rawText": null,
              "range": null,
              "shifts": null
            },
            "source": ""
          }
        ],
        "axes": {
          "x": {
            "bounds": [
              "",
              ""
            ],
            "label": "",
            "prefix": "",
            "suffix": "",
            "base": "10",
            "scale": "linear"
          },
          "y": {
            "bounds": [
              "",
              ""
            ],
            "label": "",
            "prefix": "",
            "suffix": "",
            "base": "10",
            "scale": "linear"
          },
          "y2": {
            "bounds": [
              "",
              ""
            ],
            "label": "",
            "prefix": "",
            "suffix": "",
            "base": "10",
            "scale": "linear"
          }
        },
        "type": "line",
        "colors": [
          {
            "id": "918d1196-dcca-4a61-ba54-83cbd0929dea",
            "type": "scale",
            "hex": "#31C0F6",
            "name": "Nineteen Eighty Four",
            "value": "0"
          },
          {
            "id": "ea81a8b6-ace5-4a73-a1e4-06c62d72e0cf",
            "type": "scale",
            "hex": "#A500A5",
            "name": "Nineteen Eighty Four",
            "value": "0"
          },
          {
            "id": "ebc1b6a4-5218-46b0-b1c0-89b7f1a58c9d",
            "type": "scale",
            "hex": "#FF7E27",
            "name": "Nineteen Eighty Four",
            "value": "0"
          }
        ],
        "legend": {},
        "tableOptions": {
          "verticalTimeAxis": true,
          "sortBy": {
            "internalName": "",
            "displayName": "",
            "visible": false
          },
          "wrapping": "",
          "fixFirstColumn": false
        },
        "fieldOptions": [
          {
            "internalName": "time",
            "displayName": "",
            "visible": true
          },
          {
            "internalName": "database",
            "displayName": "",
            "visible": true
          },
          {
            "internalName": "influxdb_database.Series Cardinality",
            "displayName": "",
            "visible": true
          }
        ],
        "timeFormat": "",
        "decimalPlaces": {
          "isEnforced": false,
          "digits": 3
        },
        "links": {
          "self": "/chronograf/v1/dashboards/4/cells/7e15b93e-e7ad-49b6-bffc-19d48867a21d"
        }
      },
      {
        "i": "226b6ea3-83d8-46be-9854-3f22f5de37f7",
        "x": 6,
        "y": 5,
        "w": 6,
        "h": 4,
        "name": "HTTP Request Duration (99th %)",
        "queries": [
          {
            "query": "SELECT non_negative_derivative(percentile(\"writeReqDurationNs\", 99)) /  non_negative_derivative(max(\"writeReq\")) AS \"Write Request\" FROM \"_internal\"..\"httpd\" WHERE time > :dashboardTime: GROUP BY hostname, time(:interval:) fill(0)\t",
            "queryConfig": {
              "database": "",
              "measurement": "",
              "retentionPolicy": "",
              "fields": [],
              "tags": {},
              "groupBy": {
                "time": "",
                "tags": []
              },
              "areTagsAccepted": false,
              "rawText": "SELECT non_negative_derivative(percentile(\"writeReqDurationNs\", 99)) /  non_negative_derivative(max(\"writeReq\")) AS \"Write Request\" FROM \"_internal\"..\"httpd\" WHERE time > :dashboardTime: GROUP BY hostname, time(:interval:) fill(0)\t",
              "range": null,
              "shifts": null
            },
            "source": ""
          },
          {
            "query": "SELECT non_negative_derivative(percentile(\"queryReqDurationNs\", 99)) / non_negative_derivative(max(\"queryReq\")) AS \"Query Request\" FROM \"_internal\"..\"httpd\" WHERE time > :dashboardTime: GROUP BY hostname, time(:interval:)",
            "queryConfig": {
              "database": "",
              "measurement": "",
              "retentionPolicy": "",
              "fields": [],
              "tags": {},
              "groupBy": {
                "time": "",
                "tags": []
              },
              "areTagsAccepted": false,
              "rawText": "SELECT non_negative_derivative(percentile(\"queryReqDurationNs\", 99)) / non_negative_derivative(max(\"queryReq\")) AS \"Query Request\" FROM \"_internal\"..\"httpd\" WHERE time > :dashboardTime: GROUP BY hostname, time(:interval:)",
              "range": null,
              "shifts": null
            },
            "source": ""
          }
        ],
        "axes": {
          "x": {
            "bounds": [
              "",
              ""
            ],
            "label": "",
            "prefix": "",
            "suffix": "",
            "base": "10",
            "scale": "linear"
          },
          "y": {
            "bounds": [
              "",
              ""
            ],
            "label": "",
            "prefix": "",
            "suffix": "",
            "base": "2",
            "scale": "linear"
          },
          "y2": {
            "bounds": [
              "",
              ""
            ],
            "label": "",
            "prefix": "",
            "suffix": "",
            "base": "10",
            "scale": "linear"
          }
        },
        "type": "line",
        "colors": [
          {
            "id": "731cb197-e6ac-48d5-974f-03c32ba864de",
            "type": "scale",
            "hex": "#31C0F6",
            "name": "Nineteen Eighty Four",
            "value": "0"
          },
          {
            "id": "a64b1fce-50e3-471c-a78b-2df4ed07798d",
            "type": "scale",
            "hex": "#A500A5",
            "name": "Nineteen Eighty Four",
            "value": "0"
          },
          {
            "id": "9211508a-a22c-4000-a71b-96b17c14b447",
            "type": "scale",
            "hex": "#FF7E27",
            "name": "Nineteen Eighty Four",
            "value": "0"
          }
        ],
        "legend": {},
        "tableOptions": {
          "verticalTimeAxis": false,
          "sortBy": {
            "internalName": "",
            "displayName": "",
            "visible": false
          },
          "wrapping": "",
          "fixFirstColumn": false
        },
        "fieldOptions": [],
        "timeFormat": "",
        "decimalPlaces": {
          "isEnforced": false,
          "digits": 3
        },
        "links": {
          "self": "/chronograf/v1/dashboards/4/cells/226b6ea3-83d8-46be-9854-3f22f5de37f7"
        }
      },
      {
        "i": "40ff43a6-310f-4d75-be07-ce62cbfccfbc",
        "x": 8,
        "y": 0,
        "w": 4,
        "h": 5,
        "name": "Per-Host Point Throughput/Min",
        "queries": [
          {
            "query": "SELECT non_negative_derivative(max(\"pointReq\"), 60s) FROM \"_internal\"..\"write\" WHERE time > :dashboardTime: GROUP BY time(:interval:), \"hostname\"",
            "queryConfig": {
              "database": "",
              "measurement": "",
              "retentionPolicy": "",
              "fields": [],
              "tags": {},
              "groupBy": {
                "time": "",
                "tags": []
              },
              "areTagsAccepted": false,
              "rawText": "SELECT non_negative_derivative(max(\"pointReq\"), 60s) FROM \"_internal\"..\"write\" WHERE time > :dashboardTime: GROUP BY time(:interval:), \"hostname\"",
              "range": null,
              "shifts": null
            },
            "source": ""
          }
        ],
        "axes": {
          "x": {
            "bounds": [
              "",
              ""
            ],
            "label": "",
            "prefix": "",
            "suffix": "",
            "base": "10",
            "scale": "linear"
          },
          "y": {
            "bounds": [
              "",
              ""
            ],
            "label": "",
            "prefix": "",
            "suffix": "",
            "base": "10",
            "scale": "linear"
          },
          "y2": {
            "bounds": [
              "",
              ""
            ],
            "label": "",
            "prefix": "",
            "suffix": "",
            "base": "10",
            "scale": "linear"
          }
        },
        "type": "line",
        "colors": [
          {
            "id": "731cb197-e6ac-48d5-974f-03c32ba864de",
            "type": "scale",
            "hex": "#31C0F6",
            "name": "Nineteen Eighty Four",
            "value": "0"
          },
          {
            "id": "a64b1fce-50e3-471c-a78b-2df4ed07798d",
            "type": "scale",
            "hex": "#A500A5",
            "name": "Nineteen Eighty Four",
            "value": "0"
          },
          {
            "id": "9211508a-a22c-4000-a71b-96b17c14b447",
            "type": "scale",
            "hex": "#FF7E27",
            "name": "Nineteen Eighty Four",
            "value": "0"
          }
        ],
        "legend": {},
        "tableOptions": {
          "verticalTimeAxis": false,
          "sortBy": {
            "internalName": "",
            "displayName": "",
            "visible": false
          },
          "wrapping": "",
          "fixFirstColumn": false
        },
        "fieldOptions": [],
        "timeFormat": "",
        "decimalPlaces": {
          "isEnforced": false,
          "digits": 3
        },
        "links": {
          "self": "/chronograf/v1/dashboards/4/cells/40ff43a6-310f-4d75-be07-ce62cbfccfbc"
        }
      },
      {
        "i": "9fcb29e5-7465-4a9b-a530-fb5824211513",
        "x": 0,
        "y": 0,
        "w": 4,
        "h": 5,
        "name": "Queries Executed/Min",
        "queries": [
          {
            "query": "SELECT non_negative_derivative(mean(\"queriesExecuted\"), 60s) AS \"Queries Executed\" FROM \"_internal\"..\"queryExecutor\" WHERE time > :dashboardTime: GROUP BY time(:interval:), \"hostname\" fill(null)",
            "queryConfig": {
              "database": "",
              "measurement": "",
              "retentionPolicy": "",
              "fields": [],
              "tags": {},
              "groupBy": {
                "time": "",
                "tags": []
              },
              "areTagsAccepted": false,
              "rawText": "SELECT non_negative_derivative(mean(\"queriesExecuted\"), 60s) AS \"Queries Executed\" FROM \"_internal\"..\"queryExecutor\" WHERE time > :dashboardTime: GROUP BY time(:interval:), \"hostname\" fill(null)",
              "range": null,
              "shifts": null
            },
            "source": ""
          }
        ],
        "axes": {
          "x": {
            "bounds": [
              "",
              ""
            ],
            "label": "",
            "prefix": "",
            "suffix": "",
            "base": "10",
            "scale": "linear"
          },
          "y": {
            "bounds": [
              "",
              ""
            ],
            "label": "",
            "prefix": "",
            "suffix": "",
            "base": "10",
            "scale": "linear"
          },
          "y2": {
            "bounds": [
              "",
              ""
            ],
            "label": "",
            "prefix": "",
            "suffix": "",
            "base": "10",
            "scale": "linear"
          }
        },
        "type": "line",
        "colors": [
          {
            "id": "731cb197-e6ac-48d5-974f-03c32ba864de",
            "type": "scale",
            "hex": "#31C0F6",
            "name": "Nineteen Eighty Four",
            "value": "0"
          },
          {
            "id": "a64b1fce-50e3-471c-a78b-2df4ed07798d",
            "type": "scale",
            "hex": "#A500A5",
            "name": "Nineteen Eighty Four",
            "value": "0"
          },
          {
            "id": "9211508a-a22c-4000-a71b-96b17c14b447",
            "type": "scale",
            "hex": "#FF7E27",
            "name": "Nineteen Eighty Four",
            "value": "0"
          }
        ],
        "legend": {},
        "tableOptions": {
          "verticalTimeAxis": false,
          "sortBy": {
            "internalName": "",
            "displayName": "",
            "visible": false
          },
          "wrapping": "",
          "fixFirstColumn": false
        },
        "fieldOptions": [],
        "timeFormat": "",
        "decimalPlaces": {
          "isEnforced": false,
          "digits": 3
        },
        "links": {
          "self": "/chronograf/v1/dashboards/4/cells/9fcb29e5-7465-4a9b-a530-fb5824211513"
        }
      },
      {
        "i": "605fbe18-02b6-4798-9ecb-04b1cf5f29e7",
        "x": 4,
        "y": 0,
        "w": 4,
        "h": 5,
        "name": "HTTP Requests/Min",
        "queries": [
          {
            "query": "SELECT non_negative_derivative(mean(\"queryReq\"), 60s) AS \"Query\" FROM \"_internal\"..\"httpd\" WHERE time > :dashboardTime: GROUP BY time(:interval:), \"hostname\"",
            "queryConfig": {
              "database": "",
              "measurement": "",
              "retentionPolicy": "",
              "fields": [],
              "tags": {},
              "groupBy": {
                "time": "",
                "tags": []
              },
              "areTagsAccepted": false,
              "rawText": "SELECT non_negative_derivative(mean(\"queryReq\"), 60s) AS \"Query\" FROM \"_internal\"..\"httpd\" WHERE time > :dashboardTime: GROUP BY time(:interval:), \"hostname\"",
              "range": null,
              "shifts": null
            },
            "source": ""
          },
          {
            "query": "SELECT non_negative_derivative(mean(\"writeReq\"), 60s) AS \"Writes\" FROM \"_internal\"..\"httpd\" WHERE time > :dashboardTime: GROUP BY time(:interval:), \"hostname\"",
            "queryConfig": {
              "database": "",
              "measurement": "",
              "retentionPolicy": "",
              "fields": [],
              "tags": {},
              "groupBy": {
                "time": "",
                "tags": []
              },
              "areTagsAccepted": false,
              "rawText": "SELECT non_negative_derivative(mean(\"writeReq\"), 60s) AS \"Writes\" FROM \"_internal\"..\"httpd\" WHERE time > :dashboardTime: GROUP BY time(:interval:), \"hostname\"",
              "range": null,
              "shifts": null
            },
            "source": ""
          },
          {
            "query": "SELECT non_negative_derivative(mean(\"serverError\"), 60s) AS \"Server Errors\" FROM \"_internal\"..\"httpd\" WHERE time > :dashboardTime: GROUP BY time(:interval:), \"hostname\"",
            "queryConfig": {
              "database": "",
              "measurement": "",
              "retentionPolicy": "",
              "fields": [],
              "tags": {},
              "groupBy": {
                "time": "",
                "tags": []
              },
              "areTagsAccepted": false,
              "rawText": "SELECT non_negative_derivative(mean(\"serverError\"), 60s) AS \"Server Errors\" FROM \"_internal\"..\"httpd\" WHERE time > :dashboardTime: GROUP BY time(:interval:), \"hostname\"",
              "range": null,
              "shifts": null
            },
            "source": ""
          },
          {
            "query": "SELECT non_negative_derivative(mean(\"clientError\"), 60s) AS \"Client Errors\" FROM \"_internal\"..\"httpd\" WHERE time > :dashboardTime: GROUP BY time(:interval:), \"hostname\"",
            "queryConfig": {
              "database": "",
              "measurement": "",
              "retentionPolicy": "",
              "fields": [],
              "tags": {},
              "groupBy": {
                "time": "",
                "tags": []
              },
              "areTagsAccepted": false,
              "rawText": "SELECT non_negative_derivative(mean(\"clientError\"), 60s) AS \"Client Errors\" FROM \"_internal\"..\"httpd\" WHERE time > :dashboardTime: GROUP BY time(:interval:), \"hostname\"",
              "range": null,
              "shifts": null
            },
            "source": ""
          }
        ],
        "axes": {
          "x": {
            "bounds": [
              "",
              ""
            ],
            "label": "",
            "prefix": "",
            "suffix": "",
            "base": "10",
            "scale": "linear"
          },
          "y": {
            "bounds": [
              "",
              ""
            ],
            "label": "",
            "prefix": "",
            "suffix": "",
            "base": "10",
            "scale": "linear"
          },
          "y2": {
            "bounds": [
              "",
              ""
            ],
            "label": "",
            "prefix": "",
            "suffix": "",
            "base": "10",
            "scale": "linear"
          }
        },
        "type": "line",
        "colors": [
          {
            "id": "731cb197-e6ac-48d5-974f-03c32ba864de",
            "type": "scale",
            "hex": "#31C0F6",
            "name": "Nineteen Eighty Four",
            "value": "0"
          },
          {
            "id": "a64b1fce-50e3-471c-a78b-2df4ed07798d",
            "type": "scale",
            "hex": "#A500A5",
            "name": "Nineteen Eighty Four",
            "value": "0"
          },
          {
            "id": "9211508a-a22c-4000-a71b-96b17c14b447",
            "type": "scale",
            "hex": "#FF7E27",
            "name": "Nineteen Eighty Four",
            "value": "0"
          }
        ],
        "legend": {},
        "tableOptions": {
          "verticalTimeAxis": false,
          "sortBy": {
            "internalName": "",
            "displayName": "",
            "visible": false
          },
          "wrapping": "",
          "fixFirstColumn": false
        },
        "fieldOptions": [],
        "timeFormat": "",
        "decimalPlaces": {
          "isEnforced": false,
          "digits": 3
        },
        "links": {
          "self": "/chronograf/v1/dashboards/4/cells/605fbe18-02b6-4798-9ecb-04b1cf5f29e7"
        }
      },
      {
        "i": "856e8309-8148-48a5-a73b-e9cd4fe644ab",
        "x": 0,
        "y": 17,
        "w": 6,
        "h": 4,
        "name": "Hinted HandOff Queue Size",
        "queries": [
          {
            "query": "SELECT mean(\"queueBytes\") FROM \"_internal\"..\"hh_processor\" WHERE time > :dashboardTime: GROUP BY time(:interval:), \"hostname\" fill(0)",
            "queryConfig": {
              "database": "_internal",
              "measurement": "hh_processor",
              "retentionPolicy": "",
              "fields": [
                {
                  "value": "mean",
                  "type": "func",
                  "alias": "",
                  "args": [
                    {
                      "value": "queueBytes",
                      "type": "field",
                      "alias": ""
                    }
                  ]
                }
              ],
              "tags": {},
              "groupBy": {
                "time": "auto",
                "tags": [
                  "hostname"
                ]
              },
              "areTagsAccepted": false,
              "fill": "0",
              "rawText": null,
              "range": null,
              "shifts": null
            },
            "source": ""
          }
        ],
        "axes": {
          "x": {
            "bounds": [
              "",
              ""
            ],
            "label": "",
            "prefix": "",
            "suffix": "",
            "base": "10",
            "scale": "linear"
          },
          "y": {
            "bounds": [
              "",
              ""
            ],
            "label": "",
            "prefix": "",
            "suffix": "",
            "base": "2",
            "scale": "linear"
          },
          "y2": {
            "bounds": [
              "",
              ""
            ],
            "label": "",
            "prefix": "",
            "suffix": "",
            "base": "10",
            "scale": "linear"
          }
        },
        "type": "line",
        "colors": [
          {
            "id": "731cb197-e6ac-48d5-974f-03c32ba864de",
            "type": "scale",
            "hex": "#31C0F6",
            "name": "Nineteen Eighty Four",
            "value": "0"
          },
          {
            "id": "a64b1fce-50e3-471c-a78b-2df4ed07798d",
            "type": "scale",
            "hex": "#A500A5",
            "name": "Nineteen Eighty Four",
            "value": "0"
          },
          {
            "id": "9211508a-a22c-4000-a71b-96b17c14b447",
            "type": "scale",
            "hex": "#FF7E27",
            "name": "Nineteen Eighty Four",
            "value": "0"
          }
        ],
        "legend": {},
        "tableOptions": {
          "verticalTimeAxis": false,
          "sortBy": {
            "internalName": "",
            "displayName": "",
            "visible": false
          },
          "wrapping": "",
          "fixFirstColumn": false
        },
        "fieldOptions": [],
        "timeFormat": "",
        "decimalPlaces": {
          "isEnforced": false,
          "digits": 3
        },
        "links": {
          "self": "/chronograf/v1/dashboards/4/cells/856e8309-8148-48a5-a73b-e9cd4fe644ab"
        }
      },
      {
        "i": "4bd0f414-d50a-4950-9ab3-9ab482b62ab7",
        "x": 6,
        "y": 17,
        "w": 6,
        "h": 4,
        "name": "Count of AE Errors & Jobs",
        "queries": [
          {
            "query": "SELECT non_negative_derivative(mean(\"errors\"),5m) AS \"errors\" FROM \"_internal\".\"\".\"ae\" WHERE time > :dashboardTime: GROUP BY time(:interval:) FILL(null)",
            "queryConfig": {
              "database": "",
              "measurement": "",
              "retentionPolicy": "",
              "fields": [],
              "tags": {},
              "groupBy": {
                "time": "",
                "tags": []
              },
              "areTagsAccepted": false,
              "rawText": "SELECT non_negative_derivative(mean(\"errors\"),5m) AS \"errors\" FROM \"_internal\".\"\".\"ae\" WHERE time > :dashboardTime: GROUP BY time(:interval:) FILL(null)",
              "range": null,
              "shifts": null
            },
            "source": "/chronograf/v1/sources/0"
          },
          {
            "query": "SELECT count(\"jobs_active\") AS \"count_jobs_active\" FROM \"_internal\"..\"ae\" WHERE time > :dashboardTime: GROUP BY time(:interval:) FILL(null)",
            "queryConfig": {
              "database": "_internal",
              "measurement": "ae",
              "retentionPolicy": "",
              "fields": [
                {
                  "value": "count",
                  "type": "func",
                  "alias": "count_jobs_active",
                  "args": [
                    {
                      "value": "jobs_active",
                      "type": "field",
                      "alias": ""
                    }
                  ]
                }
              ],
              "tags": {},
              "groupBy": {
                "time": "auto",
                "tags": []
              },
              "areTagsAccepted": false,
              "fill": "null",
              "rawText": null,
              "range": null,
              "shifts": null
            },
            "source": "/chronograf/v1/sources/0"
          }
        ],
        "axes": {
          "x": {
            "bounds": [
              "",
              ""
            ],
            "label": "",
            "prefix": "",
            "suffix": "",
            "base": "10",
            "scale": "linear"
          },
          "y": {
            "bounds": [
              "",
              ""
            ],
            "label": "",
            "prefix": "",
            "suffix": "",
            "base": "10",
            "scale": "linear"
          },
          "y2": {
            "bounds": [
              "",
              ""
            ],
            "label": "",
            "prefix": "",
            "suffix": "",
            "base": "10",
            "scale": "linear"
          }
        },
        "type": "line",
        "colors": [
          {
            "id": "38e011ed-6c2e-450c-8fd5-9e092ae26e4d",
            "type": "scale",
            "hex": "#31C0F6",
            "name": "Nineteen Eighty Four",
            "value": "0"
          },
          {
            "id": "c5c709aa-54a1-4401-9fbc-647a014d2b4d",
            "type": "scale",
            "hex": "#A500A5",
            "name": "Nineteen Eighty Four",
            "value": "0"
          },
          {
            "id": "da6eb413-d648-4fa1-80e5-9fcbfaeabc7e",
            "type": "scale",
            "hex": "#FF7E27",
            "name": "Nineteen Eighty Four",
            "value": "0"
          }
        ],
        "legend": {},
        "tableOptions": {
          "verticalTimeAxis": true,
          "sortBy": {
            "internalName": "time",
            "displayName": "",
            "visible": true
          },
          "wrapping": "truncate",
          "fixFirstColumn": true
        },
        "fieldOptions": [
          {
            "internalName": "time",
            "displayName": "",
            "visible": true
          }
        ],
        "timeFormat": "MM/DD/YYYY HH:mm:ss",
        "decimalPlaces": {
          "isEnforced": true,
          "digits": 2
        },
        "links": {
          "self": "/chronograf/v1/dashboards/4/cells/4bd0f414-d50a-4950-9ab3-9ab482b62ab7"
        }
      }
    ],
    "templates": [
      {
        "tempVar": ":Cluster_Id:",
        "values": [
          {
            "value": "e87a44cb9df65eb0d6fa50730842d926",
            "type": "tagValue",
            "selected": true
          }
        ],
        "id": "e4731672-e3d6-4633-b2ed-146ea51cbb7f",
        "type": "tagValues",
        "label": "",
        "query": {
          "influxql": "SHOW TAG VALUES ON :database: FROM :measurement: WITH KEY=:tagKey:",
          "db": "telegraf",
          "measurement": "cpu",
          "tagKey": "cluster_id",
          "fieldKey": ""
        },
        "links": {
          "self": "/chronograf/v1/dashboards/4/templates/e4731672-e3d6-4633-b2ed-146ea51cbb7f"
        }
      },
      {
        "tempVar": ":host:",
        "values": [
          {
            "value": "prod-edcfa83f-us-west-1-data-3",
            "type": "influxql",
            "selected": true
          }
        ],
        "id": "074f5d89-fad2-4809-b729-4fce3c9d3df9",
        "type": "influxql",
        "label": "",
        "query": {
          "influxql": "SHOW TAG VALUES ON \"telegraf\"  WITH key = \"host\" WHERE cluster_id = :Cluster_Id:",
          "measurement": "",
          "tagKey": "",
          "fieldKey": ""
        },
        "links": {
          "self": "/chronograf/v1/dashboards/4/templates/074f5d89-fad2-4809-b729-4fce3c9d3df9"
        }
      }
    ],
    "name": "InfluxDB Enterprise Cluster Stats: _internal",
    "organization": "default",
    "links": {
      "self": "/chronograf/v1/dashboards/4",
      "cells": "/chronograf/v1/dashboards/4/cells",
      "templates": "/chronograf/v1/dashboards/4/templates"
    }
  }
}
